{
  "categorias": [
    {
      "titulo": "Começando na Programação",
      "link": "https://www.alura.com.br/cursos-online-front-end",
      "cor": "#6BD1FF",
      "link_extra": {
        "text": "Cursos rápidos de Front End",
        "url": "https://www.schoolofnet.com/cursos/programacao/frontend/"
      },
      "videos": [
        {
          "titulo": "O que faz uma desenvolvedora front-end?",
          "url": "https://www.youtube.com/watch?v=ZY3-MFxVdEw"
        },  
        {
          "titulo": "Comecei a receber propostas de emprego MUITO boas por um simples motivo",
          "url": "https://www.youtube.com/watch?v=qb8yXWFRROg"
        },
        {
          "titulo": "API: Dicionário do Programador",
          "url": "https://www.youtube.com/watch?v=vGuqKIRWosk"
        }, 
        {
          "titulo": "20 PREVISÕES PARA 2020 (Programação, Web, Hospedagem, DevOps, Database, I.A., Low-code...)",
          "url": "https://www.youtube.com/watch?v=5WwFXeHSZHE"
        }
      ]
    },
    {
      "titulo": "Cursos gratuitos",
      "cor": "#00C86F",
      "link_extra": {
        "text": "Plataforma com vários cursos online para você iniciar os estudos em programação",
        "url": "https://www.schoolofnet.com/"
      },
      "videos": [
        {
          "titulo": "Curso gratuito de HTML Básico",
          "url": "https://www.schoolofnet.com/curso/frontend/html/html-basico-v2/"
        },
        {
          "titulo": "Iniciando com Javascript",
          "url": "https://www.schoolofnet.com/curso/frontend/javascript/iniciando-com-javascript-rev3/"
        },
        {
          "titulo": "",
          "url": ""
        },
        {
          "titulo": "",
          "url": ""
        }, 
        {
          "titulo": "",
          "url": ""
        }
      ]
    },
    {
      "titulo": "React",
      "cor": "#9cd33b",
      "link_extra": {
        "text": "",
        "url": ""
      },
      "videos": [
        {
          "titulo": "O que é ReactJS?",
          "url": "https://www.youtube.com/watch?v=cEczlv669Oo"
        },
        {
          "titulo": "Por que ReactJS está tão em alta?",
          "url": "https://www.youtube.com/watch?v=Hn7RBVTqtPQ"
        },
        {
          "titulo": "Imersão React Live #01 - Analisando o front-end do Netflix, do Spotify e do Ifood",
          "url": "https://www.youtube.com/watch?v=Dcn-tVmSxyU"
        }
      ]
    },
    {
      "titulo": "Ideias e projetos para programar",
      "cor": "orange",
      "videos": [
        {
          "titulo": "Mais 80 ideias para Aprender a Programar (incluindo gerar renda com Anúncios)",
          "url": "https://www.youtube.com/watch?v=H4CCPaYLTWg"
        },
        {
          "titulo": "Desafio: 10 projetos rápidos para treinar Programação e conseguir um Emprego",
          "url": "https://www.youtube.com/watch?v=fYR9L2ZmodM"
        }
      ]
    },
    {
      "titulo": "Aprendendo a aprender tecnologia",
      "cor": "#6b5be2",
      "link_extra": {
        "text": "Curso sobre aprendizado na Alura",
        "url": "https://alura.com.br/curso-online-aprender-a-aprender-tecnicas-para-seu-autodesenvolvimento"
      },
      "videos": [
        {
          "titulo": "Como estudar melhor?",
          "url": "https://www.youtube.com/watch?v=Is6c9KSGCbk&feature=youtu.be"
        },
        {
          "titulo": "Faculdade",
          "url": "https://www.youtube.com/watch?v=jw06H8esyzQ&feature=youtu.be"
        },
        {
          "titulo": "Frameworks",
          "url": "https://www.youtube.com/watch?v=QzDjdlF1BQI"
        },
        {
          "titulo": "A mágica do Aprendizado",
          "url": "https://www.youtube.com/watch?v=oTEXzpfEpPY"
        },
        {
          "titulo": "Como aprender a programar?",
          "url": "https://www.youtube.com/watch?v=MwCx2qKdbDw&feature=youtu.be"
        }
      ]
    }
  ]
}